cuttly/__init__.py
cuttly/main.py
cuttly/models.py
cuttly/utils.py
cuttly_service-0.1.0.dist-info/METADATA
cuttly_service-0.1.0.dist-info/WHEEL
cuttly_service-0.1.0.dist-info/top_level.txt
cuttly_service-0.1.0.dist-info/RECORD
