Metadata-Version: 2.4
Name: cuttly-service
Version: 0.1.0
Summary: short url
Home-page: https://github.com/selviler/cuttly-service
Author: slvler
Author-email: slvler@proton.me
License: MIT
Project-URL: Homepage, https://github.com/selviler/cuttly-service
Requires-Python: >=3.9.6
Requires-Dist: requests>=2.32.4
Requires-Dist: python-dotenv>=1.0.1
Requires-Dist: pydantic>=2.10.4
Dynamic: author-email
Dynamic: home-page
Dynamic: requires-python
